{
  "name": "MAX7XX-7-Segment",
  "version": "1.1.0",
  "description": "A library for driving a 7-segment display driven with a MAX7219 or MAX7221 IC.",
  "keywords": "display, MAX7219, MAX7221, 7-segment",
  "repository":
  {
    "type": "git",
    "url": "https://github.com/abaskin/MAX7XX"
  },
  "authors":
  [
    {
      "name": "Andre Baskin",
      "email": "andre@telatomica.com",
      "url": "https://github.com/abaskin",
      "maintainer": true
    }
  ],
  "license": "MIT",
  "homepage": "",
  "exclude": [
    ".github"
  ],
  "frameworks": "arduino",
  "platforms": "*"
}
